<?xml version="1.0" encoding="utf-8"?>
<Dependencies>
  <!-- Periodically run "powershell eng\common\darc-init.ps1" to update the Darc version. -->
  <ProductDependencies>
  </ProductDependencies>
  <ToolsetDependencies>
    <Dependency Name="Microsoft.DotNet.Arcade.Sdk" Version="11.0.0-beta.26210.2">
      <Uri>https://github.com/dotnet/arcade</Uri>
      <Sha>4ba1b1c0c6bceb23e9475d40ae1b16f825a5e19b</Sha>
    </Dependency>
    <Dependency Name="Microsoft.DotNet.GenFacades" Version="11.0.0-beta.26210.2">
      <Uri>https://github.com/dotnet/arcade</Uri>
      <Sha>4ba1b1c0c6bceb23e9475d40ae1b16f825a5e19b</Sha>
    </Dependency>
    <Dependency Name="Microsoft.DotNet.XUnitExtensions" Version="11.0.0-beta.26210.2">
      <Uri>https://github.com/dotnet/arcade</Uri>
      <Sha>4ba1b1c0c6bceb23e9475d40ae1b16f825a5e19b</Sha>
    </Dependency>
    <Dependency Name="Microsoft.DotNet.GenAPI" Version="11.0.0-beta.26210.2">
      <Uri>https://github.com/dotnet/arcade</Uri>
      <Sha>4ba1b1c0c6bceb23e9475d40ae1b16f825a5e19b</Sha>
    </Dependency>
    <Dependency Name="Microsoft.DotNet.Helix.Sdk" Version="11.0.0-beta.26210.2">
      <Uri>https://github.com/dotnet/arcade</Uri>
      <Sha>4ba1b1c0c6bceb23e9475d40ae1b16f825a5e19b</Sha>
    </Dependency>
  </ToolsetDependencies>
</Dependencies>
