<?xml version="1.0" encoding="utf-8"?>
<Dependencies>
  <!-- Periodically run "powershell eng\common\darc-init.ps1" to update the Darc version. -->
  <ProductDependencies>
  </ProductDependencies>
  <ToolsetDependencies>
    <Dependency Name="Microsoft.DotNet.Arcade.Sdk" Version="9.0.0-beta.24428.1">
      <Uri>https://github.com/dotnet/arcade</Uri>
      <Sha>8c014d39b54295c36f61636aa897a6fe6c25c902</Sha>
    </Dependency>
    <Dependency Name="Microsoft.DotNet.GenFacades" Version="9.0.0-beta.24428.1">
      <Uri>https://github.com/dotnet/arcade</Uri>
      <Sha>8c014d39b54295c36f61636aa897a6fe6c25c902</Sha>
    </Dependency>
    <Dependency Name="Microsoft.DotNet.XUnitExtensions" Version="9.0.0-beta.24428.1">
      <Uri>https://github.com/dotnet/arcade</Uri>
      <Sha>8c014d39b54295c36f61636aa897a6fe6c25c902</Sha>
    </Dependency>
  </ToolsetDependencies>
</Dependencies>
