<?xml version="1.0" encoding="utf-8"?>
<Dependencies>
  <!-- Periodically run "powershell eng\common\darc-init.ps1" to update the Darc version. -->
  <ProductDependencies>
  </ProductDependencies>
  <ToolsetDependencies>
    <Dependency Name="Microsoft.DotNet.Arcade.Sdk" Version="10.0.0-beta.25204.12">
      <Uri>https://github.com/dotnet/arcade</Uri>
      <Sha>25bd3926321ea9b6ca66c772e03a76e7a5010227</Sha>
    </Dependency>
    <Dependency Name="Microsoft.DotNet.GenFacades" Version="10.0.0-beta.25204.12">
      <Uri>https://github.com/dotnet/arcade</Uri>
      <Sha>25bd3926321ea9b6ca66c772e03a76e7a5010227</Sha>
    </Dependency>
    <Dependency Name="Microsoft.DotNet.XUnitExtensions" Version="10.0.0-beta.25204.12">
      <Uri>https://github.com/dotnet/arcade</Uri>
      <Sha>25bd3926321ea9b6ca66c772e03a76e7a5010227</Sha>
    </Dependency>
  </ToolsetDependencies>
</Dependencies>
